lyric_probe_performance/__init__.py
lyric_probe_performance/controller.py
lyric_probe_performance/main.py
lyric_probe_performance/routes.py
lyric_probe_performance/runner.py
lyric_probe_performance/controllers/__init__.py
lyric_probe_performance/controllers/base_controller.py
lyric_probe_performance/controllers/external_actions.py
lyric_probe_performance/controllers/external_apps.py
lyric_probe_performance/controllers/external_scenarios.py
lyric_probe_performance/controllers/external_tables.py
lyric_probe_performance/controllers/external_token.py
lyric_probe_performance/tasks/__init__.py
lyric_probe_performance/tasks/action_task.py
lyric_probe_performance/tasks/base_task.py
lyric_probe_performance/tasks/scenario_task.py
lyric_probe_performance/tasks/tasks.py
lyric_probe_performance/tasks/tasks_copy.py
lyric_probe_performance/tasks/upload_task.py
lyric_probe_performance/tasks/user_task.py
lyric_probe_performance/utils/__init__.py
lyric_probe_performance/utils/auth_manager.py
lyric_probe_performance/utils/base_setup.py
lyric_probe_performance/utils/config_loader.py
lyric_probe_performance/utils/download_manager.py
lyric_probe_performance/utils/exceptions.py
lyric_probe_performance/utils/log_manager.py
lyric_probe_performance/utils/report_manager.py
lyric_probe_performance/utils/setup_manager.py
lyric_probe_performance/utils/teardown.py
lyric_probe_performance/utils/token_manager.py
lyric_probe_performance/utils/upload_manager.py
lyric_probe_performance-0.1.dist-info/METADATA
lyric_probe_performance-0.1.dist-info/WHEEL
lyric_probe_performance-0.1.dist-info/top_level.txt
lyric_probe_performance-0.1.dist-info/RECORD
