Metadata-Version: 2.2
Name: lyric-probe-performance
Version: 0.1
Requires-Dist: locust>=2.32.5
Requires-Dist: requests>=2.32.3
Requires-Dist: requests-toolbelt>=1.0.0
Requires-Dist: urllib3>=2.2.3
Requires-Dist: pyyaml>=6.0.1
Requires-Dist: python-dateutil>=2.8.2
Requires-Dist: pandas>=2.0.0
Requires-Dist: pytest>=7.0.0
Requires-Dist: pytest-cov>=4.0.0
Dynamic: requires-dist
